ditenz/__init__.py
ditenz/courses.py
ditenz/utils.py
test_no_funcional-0.1.1.dist-info/METADATA
test_no_funcional-0.1.1.dist-info/WHEEL
test_no_funcional-0.1.1.dist-info/top_level.txt
test_no_funcional-0.1.1.dist-info/RECORD
