Metadata-Version: 2.4
Name: test_no_funcional
Version: 0.1.1
Summary: Consultas de cursos
Author: Ditenz
Dynamic: author
Dynamic: description
Dynamic: description-content-type
Dynamic: summary
